twitterbot/__init__.py
twitterbot/bot.py
twitterbot2-0.0.2.dist-info/AUTHORS.rst
twitterbot2-0.0.2.dist-info/LICENSE
twitterbot2-0.0.2.dist-info/METADATA
twitterbot2-0.0.2.dist-info/WHEEL
twitterbot2-0.0.2.dist-info/top_level.txt
twitterbot2-0.0.2.dist-info/RECORD
