Metadata-Version: 2.1
Name: twitterbot2
Version: 0.0.2
Summary: Python Boilerplate contains all the boilerplate you need to create a Python package.
Home-page: https://github.com/aniversarioperu/twitterbot
Author: Yoni Pacheco
Author-email: aniversarioperu1@gmail.com
License: ISCL
Keywords: twitterbot
Platform: UNKNOWN
Classifier: Development Status :: 2 - Pre-Alpha
Classifier: Intended Audience :: Developers
Classifier: License :: OSI Approved :: ISC License (ISCL)
Classifier: Natural Language :: English
Classifier: Programming Language :: Python :: 2.7
Classifier: Programming Language :: Python :: 3.5
Classifier: Programming Language :: Python :: 3.6
Classifier: Programming Language :: Python :: 3.7
Requires-Dist: requests
Requires-Dist: requests-oauthlib
